napari_tools_menu/__init__.py
napari_tools_menu-0.1.20.dist-info/LICENSE
napari_tools_menu-0.1.20.dist-info/METADATA
napari_tools_menu-0.1.20.dist-info/WHEEL
napari_tools_menu-0.1.20.dist-info/entry_points.txt
napari_tools_menu-0.1.20.dist-info/top_level.txt
napari_tools_menu-0.1.20.dist-info/RECORD
